Multi_Output/Classification.py
Multi_Output/ClassificationGrid.py
Multi_Output/Regression.py
Multi_Output/RegressionGrid.py
Multi_Output/__init__.py
Single_Output/Classification.py
Single_Output/ClassificationGrid.py
Single_Output/Regression.py
Single_Output/RegressionGrid.py
Single_Output/__init__.py
SciLite-0.0.1.dist-info/METADATA
SciLite-0.0.1.dist-info/WHEEL
SciLite-0.0.1.dist-info/top_level.txt
SciLite-0.0.1.dist-info/RECORD
