Metadata-Version: 2.1
Name: SciLite
Version: 0.0.1
Summary: Sci-Lite is Light version of Supervised Machine Learning Model
Home-page: https://github.com/yourusername/my_package
Author: Ayush Jain Sparsh
Author-email: ayushjainsparsh2004.ajs@gmail.com
Classifier: Programming Language :: Python :: 3
Classifier: License :: OSI Approved :: MIT License
Classifier: Operating System :: OS Independent
Requires-Python: >=3.6
Requires-Dist: pandas
Requires-Dist: scikit-learn
Requires-Dist: catboost
